Metadata-Version: 2.1
Name: oozie-webservice-api
Version: 1.2.0
Summary: Python wrapper for Oozie Webservice REST API
Home-page: https://github.com/developer-sdk/oozie-webservice-api
Author: hs_seo
Author-email: fluorite118@gmail.com
License: MIT
Download-URL: https://github.com/developer-sdk/oozie-webservice-api/archive/master.zip
Keywords: oozie,webservice,api
Platform: UNKNOWN
Classifier: Programming Language :: Python :: 2
Classifier: Programming Language :: Python :: 3
Classifier: License :: OSI Approved :: MIT License
Classifier: Operating System :: OS Independent
